llm_etl_pipeline/__init__.py
llm_etl_pipeline/customized_logger/__init__.py
llm_etl_pipeline/customized_logger/loggers.py
llm_etl_pipeline/extraction/__init__.py
llm_etl_pipeline/extraction/internal/__init__.py
llm_etl_pipeline/extraction/internal/filters.py
llm_etl_pipeline/extraction/internal/template/prompts/dirty.j2
llm_etl_pipeline/extraction/internal/template/prompts/prompt_message.j2
llm_etl_pipeline/extraction/internal/template/system/system_message.j2
llm_etl_pipeline/extraction/internal/utils.py
llm_etl_pipeline/extraction/public/__init__.py
llm_etl_pipeline/extraction/public/converters/__init__.py
llm_etl_pipeline/extraction/public/converters/pdfconverters.py
llm_etl_pipeline/extraction/public/documents.py
llm_etl_pipeline/extraction/public/localllms.py
llm_etl_pipeline/extraction/public/paragraphs.py
llm_etl_pipeline/extraction/public/parsers/_init__.py
llm_etl_pipeline/extraction/public/parsers/entities.py
llm_etl_pipeline/extraction/public/parsers/monetary_informations.py
llm_etl_pipeline/extraction/public/sentences.py
llm_etl_pipeline/extraction/public/utils.py
llm_etl_pipeline/transformation/__init__.py
llm_etl_pipeline/transformation/internal/__init__.py
llm_etl_pipeline/transformation/internal/utils.py
llm_etl_pipeline/transformation/public/__init__.py
llm_etl_pipeline/transformation/public/pipelines.py
llm_etl_pipeline/transformation/public/transformation_functions.py
llm_etl_pipeline/transformation/public/utils.py
llm_etl_pipeline/typings/__init__.py
llm_etl_pipeline/typings/internal/__init__.py
llm_etl_pipeline/typings/internal/validators.py
llm_etl_pipeline/typings/public/__init__.py
llm_etl_pipeline/typings/public/aliases.py
llm_etl_pipeline-0.1.0.dist-info/LICENSE
llm_etl_pipeline-0.1.0.dist-info/METADATA
llm_etl_pipeline-0.1.0.dist-info/NOTICE
llm_etl_pipeline-0.1.0.dist-info/WHEEL
llm_etl_pipeline-0.1.0.dist-info/RECORD
