Metadata-Version: 2.3
Name: llm_etl_pipeline
Version: 0.1.0
Summary: LLM extraction from documents
License: Apache-2.0
Keywords: artificial-intelligence,automated-prompting,data-extraction,document,document-analysis,document-extraction,document-intelligence,document-parsing,document-pipeline,document-processing,document-qa,document-understanding,generative-ai,information-extraction,insights-extraction,knowledge-extraction,large-language-models,llm,llm-extraction,llm-framework,llm-library,llm-reasoning,machine-learning,multilingual,multimodal,neural-segmentation,zero-shot
Author: Albert Bellumat
Author-email: albertobellumat@gmail.com
Maintainer: Albert Bellumat
Maintainer-email: albertobellumat@gmail.com
Requires-Python: >=3.10,<3.14
Classifier: Topic :: Text Processing :: General
Requires-Dist: aiolimiter (>=1.2.1,<2.0.0)
Requires-Dist: docling (>=2.36.1,<3.0.0)
Requires-Dist: duckduckgo-search (>=8.0.4,<9.0.0)
Requires-Dist: jinja2 (>=3.1.5,<4.0.0)
Requires-Dist: langchain (>=0.3.25,<0.4.0)
Requires-Dist: langchain-community (>=0.3.25,<0.4.0)
Requires-Dist: langchain-google-community (>=2.0.7,<3.0.0)
Requires-Dist: langchain-ollama (>=0.3.3,<0.4.0)
Requires-Dist: litellm (>=1.68.0,<1.71.2)
Requires-Dist: loguru (>=0.7.3,<0.8.0)
Requires-Dist: nest-asyncio (>=1.6.0,<2.0.0)
Requires-Dist: pdfplumber (>=0.11.6,<0.12.0)
Requires-Dist: pydantic (>=2.10.6,<3.0.0)
Requires-Dist: pymupdf (>=1.26.0,<2.0.0)
Requires-Dist: python-ulid (>=3.0.0,<4.0.0)
Requires-Dist: sentence-transformers (>=4.1.0,<5.0.0)
Requires-Dist: wtpsplit-lite (>=0.1.0,<0.2.0)
